Day6/seq_detector.v
module seq_detector(
  input clk,
  input reset,
  input din,
  output reg detected
);

parameter S0 = 3'b000;
parameter S1 = 3'b001;
parameter S2 = 3'b010;
parameter S3 = 3'b011;
parameter S4 = 3'b100;

reg [2:0] current_state;
reg [2:0] next_state;

// State Register
always @(posedge clk or posedge reset)
begin
  if(reset)
    current_state <= S0;
  else
    current_state <= next_state;
end

// Next State Logic
always @(*)
begin
  case(current_state)
    S0: next_state = din ? S1 : S0;
    S1: next_state = din ? S1 : S2;
    S2: next_state = din ? S3 : S0;
    S3: next_state = din ? S4 : S2;
    S4: next_state = din ? S1 : S0;
    default: next_state = S0;
  endcase
end

// Output Logic
always @(*)
begin
  detected = (current_state == S4) ? 1 : 0;
end

endmodule

Day6/tb_seq_detector.v
module tb_seq_detector;

  reg clk, reset, din;
  wire detected;

  seq_detector uut(
    .clk(clk),
    .reset(reset),
    .din(din),
    .detected(detected)
  );

  always #5 clk = ~clk;

  initial begin
    $dumpfile("seq_detector.vcd");
    $dumpvars(0, tb_seq_detector);

    clk = 0;
    reset = 1; #10;
    reset = 0;

    // Send sequence 1011
    din = 1; #10;
    din = 0; #10;
    din = 1; #10;
    din = 1; #10;

    // Send again
    din = 1; #10;
    din = 0; #10;
    din = 1; #10;
    din = 1; #10;

    $finish;
  end

endmodule

Day6/seq_detector.vcd
$date
	Thu Apr  2 04:26:52 2026
$end
$version
	Icarus Verilog
$end
$timescale
	1s
$end
$scope module tb_seq_detector $end
$var wire 1 ! detected $end
$var reg 1 " clk $end
$var reg 1 # din $end
$var reg 1 $ reset $end
$scope module uut $end
$var wire 1 " clk $end
$var wire 1 # din $end
$var wire 1 $ reset $end
$var parameter 3 % S0 $end
$var parameter 3 & S1 $end
$var parameter 3 ' S2 $end
$var parameter 3 ( S3 $end
$var parameter 3 ) S4 $end
$var reg 3 * current_state [2:0] $end
$var reg 1 ! detected $end
$var reg 3 + next_state [2:0] $end
$upscope $end
$upscope $end
$enddefinitions $end
$comment Show the parameter values. $end
$dumpall
b100 )
b11 (
b10 '
b1 &
b0 %
$end
#0
$dumpvars
b0x +
b0 *
1$
x#
0"
0!
$end
#5
1"
#10
b1 +
0"
1#
0$
#15
b1 *
1"
#20
b10 +
0"
0#
#25
b0 +
b10 *
1"
#30
b11 +
0"
1#
#35
b100 +
b11 *
1"
#40
0"
#45
1!
b1 +
b100 *
1"
#50
0"
#55
0!
b1 *
1"
#60
b10 +
0"
0#
#65
b0 +
b10 *
1"
#70
b11 +
0"
1#
#75
b100 +
b11 *
1"
#80
0"
#85
1!
b1 +
b100 *
1"
