Day6/traffic_light.v
module traffic_light(
  input clk,
  input reset,
  output reg red,
  output reg yellow,
  output reg green
);

parameter RED    = 2'b00;
parameter YELLOW = 2'b01;
parameter GREEN  = 2'b10;

reg [1:0] current_state;
reg [1:0] next_state;

// State counter
reg [3:0] count;

// State Register
always @(posedge clk or posedge reset)
begin
  if(reset)
    begin
      current_state <= RED;
      count <= 0;
    end
  else
    begin
      if(count == 4'd9)
        begin
          current_state <= next_state;
          count <= 0;
        end
      else
        count <= count + 1;
    end
end

// Next State Logic
always @(*)
begin
  case(current_state)
    RED:    next_state = GREEN;
    GREEN:  next_state = YELLOW;
    YELLOW: next_state = RED;
    default: next_state = RED;
  endcase
end

// Output Logic
always @(*)
begin
  red    = 0;
  yellow = 0;
  green  = 0;
  case(current_state)
    RED:    red    = 1;
    GREEN:  green  = 1;
    YELLOW: yellow = 1;
  endcase
end

endmodule

Day6/tb_traffic_light.v
module tb_traffic_light;

  reg clk, reset;
  wire red, yellow, green;

  traffic_light uut(
    .clk(clk),
    .reset(reset),
    .red(red),
    .yellow(yellow),
    .green(green)
  );

  always #5 clk = ~clk;

  initial begin
    $dumpfile("traffic_light.vcd");
    $dumpvars(0, tb_traffic_light);

    clk = 0;
    reset = 1; #10;
    reset = 0; #400;

    $finish;
  end

endmodule

Day6/traffic_light.vcd
$date
	Thu Apr  2 04:25:34 2026
$end
$version
	Icarus Verilog
$end
$timescale
	1s
$end
$scope module tb_traffic_light $end
$var wire 1 ! yellow $end
$var wire 1 " red $end
$var wire 1 # green $end
$var reg 1 $ clk $end
$var reg 1 % reset $end
$scope module uut $end
$var wire 1 $ clk $end
$var wire 1 % reset $end
$var parameter 2 & GREEN $end
$var parameter 2 ' RED $end
$var parameter 2 ( YELLOW $end
$var reg 4 ) count [3:0] $end
$var reg 2 * current_state [1:0] $end
$var reg 1 # green $end
$var reg 2 + next_state [1:0] $end
$var reg 1 " red $end
$var reg 1 ! yellow $end
$upscope $end
$upscope $end
$enddefinitions $end
$comment Show the parameter values. $end
$dumpall
b1 (
b0 '
b10 &
$end
#0
$dumpvars
b10 +
b0 *
b0 )
1%
0$
0#
1"
0!
$end
#5
1$
#10
0$
0%
#15
b1 )
1$
#20
0$
#25
b10 )
1$
#30
0$
#35
b11 )
1$
#40
0$
#45
b100 )
1$
#50
0$
#55
b101 )
1$
#60
0$
#65
b110 )
1$
#70
0$
#75
b111 )
1$
#80
0$
#85
b1000 )
1$
#90
0$
#95
b1001 )
1$
#100
0$
#105
b1 +
1#
0"
b0 )
b10 *
1$
#110
0$
#115
b1 )
1$
#120
0$
#125
b10 )
1$
#130
0$
#135
b11 )
1$
#140
0$
#145
b100 )
1$
#150
0$
#155
b101 )
1$
#160
0$
#165
b110 )
1$
#170
0$
#175
b111 )
1$
#180
0$
#185
b1000 )
1$
#190
0$
#195
b1001 )
1$
#200
0$
#205
1!
0#
b0 +
b0 )
b1 *
1$
#210
0$
#215
b1 )
1$
#220
0$
#225
b10 )
1$
#230
0$
#235
b11 )
1$
#240
0$
#245
b100 )
1$
#250
0$
#255
b101 )
1$
#260
0$
#265
b110 )
1$
#270
0$
#275
b111 )
1$
#280
0$
#285
b1000 )
1$
#290
0$
#295
b1001 )
1$
#300
0$
#305
b10 +
1"
0!
b0 )
b0 *
1$
#310
0$
#315
b1 )
1$
#320
0$
#325
b10 )
1$
#330
0$
#335
b11 )
1$
#340
0$
#345
b100 )
1$
#350
0$
#355
b101 )
1$
#360
0$
#365
b110 )
1$
#370
0$
#375
b111 )
1$
#380
0$
#385
b1000 )
1$
#390
0$
#395
b1001 )
1$
#400
0$
#405
1#
0"
b1 +
b0 )
b10 *
1$
