dff_sync_reset.v
module dff_sync_reset(
  input clk,
  input sync_reset,
  input d,
  output reg q
);

always @(posedge clk)
begin
  if(sync_reset)
    q <= 1'b0;
  else
    q <= d;
end

endmodule

tb_dff_sync_reset.v
module tb_dff_sync_reset;

  reg clk, sync_reset, d;
  wire q;

  dff_sync_reset uut(
    .clk(clk),
    .sync_reset(sync_reset),
    .d(d),
    .q(q)
  );

  always #5 clk = ~clk;

  initial begin
    $dumpfile("dff_sync_reset.vcd");
    $dumpvars(0, tb_dff_sync_reset);

    clk = 0;
    sync_reset = 1;
    d = 0;
    #10;

    sync_reset = 0;
    d = 1; #10;
    d = 0; #10;
    d = 1; #10;

    sync_reset = 1; #10;
    sync_reset = 0;
    d = 1; #10;
    d = 0; #10;

    $finish;
  end

endmodule

Day4/dff_sync_reset.vcd
$date
	Tue Mar 31 09:21:00 2026
$end
$version
	Icarus Verilog
$end
$timescale
	1s
$end
$scope module tb_dff_sync_reset $end
$var wire 1 ! q $end
$var reg 1 " clk $end
$var reg 1 # d $end
$var reg 1 $ sync_reset $end
$scope module uut $end
$var wire 1 " clk $end
$var wire 1 # d $end
$var wire 1 $ sync_reset $end
$var reg 1 ! q $end
$upscope $end
$upscope $end
$enddefinitions $end
$comment Show the parameter values. $end
$dumpall
$end
#0
$dumpvars
1$
0#
0"
x!
$end
#5
0!
1"
#10
0"
1#
0$
#15
1!
1"
#20
0"
0#
#25
0!
1"
#30
0"
1#
#35
1!
1"
#40
0"
1$
#45
0!
1"
#50
0"
0$
#55
1!
1"
#60
0"
0#
#65
0!
1"
