Day4/dff_async_reset.v
module dff_async_reset(
  input clk,
  input async_reset,
  input d,
  output reg q
);

always @(posedge clk or posedge async_reset)
begin
  if(async_reset)
    q <= 1'b0;
  else
    q <= d;
end

endmodule

Day4/tb_dff_async_reset.v
module tb_dff_async_reset;

  reg clk, async_reset, d;
  wire q;

  dff_async_reset uut(
    .clk(clk),
    .async_reset(async_reset),
    .d(d),
    .q(q)
  );

  always #5 clk = ~clk;

  initial begin
    $dumpfile("dff_async_reset.vcd");
    $dumpvars(0, tb_dff_async_reset);

    clk = 0;
    async_reset = 1;
    d = 0;
    #10;

    async_reset = 0;
    d = 1; #10;
    d = 0; #10;
    d = 1; #10;

    async_reset = 1; #10;
    async_reset = 0;
    d = 1; #10;
    d = 0; #10;

    $finish;
  end

endmodule

Day4/dff_async_reset.vcd
$date
	Tue Mar 31 09:20:39 2026
$end
$version
	Icarus Verilog
$end
$timescale
	1s
$end
$scope module tb_dff_async_reset $end
$var wire 1 ! q $end
$var reg 1 " async_reset $end
$var reg 1 # clk $end
$var reg 1 $ d $end
$scope module uut $end
$var wire 1 " async_reset $end
$var wire 1 # clk $end
$var wire 1 $ d $end
$var reg 1 ! q $end
$upscope $end
$upscope $end
$enddefinitions $end
$comment Show the parameter values. $end
$dumpall
$end
#0
$dumpvars
0$
0#
1"
0!
$end
#5
1#
#10
0#
1$
0"
#15
1!
1#
#20
0#
0$
#25
0!
1#
#30
0#
1$
#35
1!
1#
#40
0!
0#
1"
#45
1#
#50
0#
0"
#55
1!
1#
#60
0#
0$
#65
0!
1#
