src/alu.v
module alu(
  input [7:0] a,
  input [7:0] b,
  input [2:0] op,
  output reg [7:0] result,
  output reg zero
);

always @(*)
begin 
 case (op)
   3'b000: result = a + b ;
   3'b001: result = a - b;
   3'b010: result = a & b;
   3'b011: result = a | b;
   3'b100: result = a ^ b;
   3'b101: result = ~a;
   3'b110: result = a << 1;
   3'b111: result = a >> 1;
   default: result = 8'b0;
endcase 
zero = (result == 8'b0) ? 1 : 0 ;
end 
endmodule

Day7/tb_alu.v
module tb_alu;

  reg [7:0] a, b;
  reg [2:0] op;
  wire [7:0] result;
  wire zero;

  alu uut(
    .a(a),
    .b(b),
    .op(op),
    .result(result),
    .zero(zero)
  );

  initial begin
    $dumpfile("alu.vcd");
    $dumpvars(0, tb_alu);

    // Addition
    a = 8'd10; b = 8'd5;
    op = 3'b000; #10;

    // Subtraction
    a = 8'd10; b = 8'd5;
    op = 3'b001; #10;

    // AND
    a = 8'hFF; b = 8'h0F;
    op = 3'b010; #10;

    // OR
    a = 8'hF0; b = 8'h0F;
    op = 3'b011; #10;

    // XOR
    a = 8'hFF; b = 8'hFF;
    op = 3'b100; #10;

    // NOT
    a = 8'hFF; b = 8'h00;
    op = 3'b101; #10;

    // Left Shift
    a = 8'b00001111; b = 8'h00;
    op = 3'b110; #10;

    // Right Shift
    a = 8'b11110000; b = 8'h00;
    op = 3'b111; #10;

    $finish;
  end

endmodule

Day7/alu.vcd
$date
	Fri Apr  3 00:11:51 2026
$end
$version
	Icarus Verilog
$end
$timescale
	1s
$end
$scope module tb_alu $end
$var wire 1 ! zero $end
$var wire 8 " result [7:0] $end
$var reg 8 # a [7:0] $end
$var reg 8 $ b [7:0] $end
$var reg 3 % op [2:0] $end
$scope module uut $end
$var wire 8 & a [7:0] $end
$var wire 8 ' b [7:0] $end
$var wire 3 ( op [2:0] $end
$var reg 8 ) result [7:0] $end
$var reg 1 ! zero $end
$upscope $end
$upscope $end
$enddefinitions $end
$comment Show the parameter values. $end
$dumpall
$end
#0
$dumpvars
b1111 )
b0 (
b101 '
b1010 &
b0 %
b101 $
b1010 #
b1111 "
0!
$end
#10
b101 "
b101 )
b1 %
b1 (
#20
b1111 "
b1111 )
b10 %
b10 (
b1111 $
b1111 '
b11111111 #
b11111111 &
#30
b11111111 "
b11111111 )
b11 %
b11 (
b11110000 #
b11110000 &
#40
1!
b0 "
b0 )
b100 %
b100 (
b11111111 $
b11111111 '
b11111111 #
b11111111 &
#50
b101 %
b101 (
b0 $
b0 '
#60
0!
b11110 "
b11110 )
b110 %
b110 (
b1111 #
b1111 &
#70
b1111000 "
b1111000 )
b111 %
b111 (
b11110000 #
b11110000 &
