Day5/up_counter.v
module up_counter(
  input clk,
  input reset,
  output reg [3:0] count
);

always @(posedge clk or posedge reset)
begin
  if(reset)
    count <= 4'b0000;
  else
    count <= count + 1;
end

endmodule

Day5/tb_up_counter.v
module tb_up_counter;

  reg clk, reset;
  wire [3:0] count;

  up_counter uut(
    .clk(clk),
    .reset(reset),
    .count(count)
  );

  always #5 clk = ~clk;

  initial begin
    $dumpfile("up_counter.vcd");
    $dumpvars(0, tb_up_counter);

    clk = 0;
    reset = 1; #10;
    reset = 0; #160;

    $finish;
  end

endmodule

Day5/up_counter.vcd
$date
	Tue Mar 31 23:41:58 2026
$end
$version
	Icarus Verilog
$end
$timescale
	1s
$end
$scope module tb_up_counter $end
$var wire 4 ! count [3:0] $end
$var reg 1 " clk $end
$var reg 1 # reset $end
$scope module uut $end
$var wire 1 " clk $end
$var wire 1 # reset $end
$var reg 4 $ count [3:0] $end
$upscope $end
$upscope $end
$enddefinitions $end
$comment Show the parameter values. $end
$dumpall
$end
#0
$dumpvars
b0 $
1#
0"
b0 !
$end
#5
1"
#10
0"
0#
#15
b1 !
b1 $
1"
#20
0"
#25
b10 !
b10 $
1"
#30
0"
#35
b11 !
b11 $
1"
#40
0"
#45
b100 !
b100 $
1"
#50
0"
#55
b101 !
b101 $
1"
#60
0"
#65
b110 !
b110 $
1"
#70
0"
#75
b111 !
b111 $
1"
#80
0"
#85
b1000 !
b1000 $
1"
#90
0"
#95
b1001 !
b1001 $
1"
#100
0"
#105
b1010 !
b1010 $
1"
#110
0"
#115
b1011 !
b1011 $
1"
#120
0"
#125
b1100 !
b1100 $
1"
#130
0"
#135
b1101 !
b1101 $
1"
#140
0"
#145
b1110 !
b1110 $
1"
#150
0"
#155
b1111 !
b1111 $
1"
#160
0"
#165
b0 !
b0 $
1"
