Day13/src/uart_tx.v
module uart_tx(
  input clk,
  input reset,
  input start,
  input [7:0] data,
  output reg tx,
  output reg done
);

parameter IDLE  = 2'b00;
parameter START = 2'b01;
parameter DATA  = 2'b10;
parameter STOP  = 2'b11;

reg [1:0] state;
reg [2:0] bit_count;
reg [7:0] data_reg;

always @(posedge clk or posedge reset)
begin
  if(reset)
    begin
      state     <= IDLE;
      tx        <= 1'b1;
      done      <= 1'b0;
      bit_count <= 0;
    end
  else
    begin
      case(state)
        IDLE:
          begin
            tx   <= 1'b1;
            done <= 1'b0;
            if(start)
              begin
                state    <= START;
                data_reg <= data;
              end
          end

        START:
          begin
            tx        <= 1'b0;
            bit_count <= 0;
            state     <= DATA;
          end

        DATA:
          begin
            tx <= data_reg[bit_count];
            if(bit_count == 3'd7)
              state <= STOP;
            else
              bit_count <= bit_count + 1;
          end

        STOP:
          begin
            tx    <= 1'b1;
            done  <= 1'b1;
            state <= IDLE;
          end
      endcase
    end
end

endmodule

Day8/tb_uart_tx.v
module tb_uart_tx;

  reg clk, reset, start;
  reg [7:0] data;
  wire tx, done;

  uart_tx uut(
    .clk(clk),
    .reset(reset),
    .start(start),
    .data(data),
    .tx(tx),
    .done(done)
  );

  always #5 clk = ~clk;

  initial begin
    $dumpfile("uart_tx.vcd");
    $dumpvars(0, tb_uart_tx);

    clk   = 0;
    reset = 1;
    start = 0;
    data  = 8'b0;
    #10;

    reset = 0;
    data  = 8'b10101010;
    start = 1; #10;
    start = 0; #100;

    data  = 8'b11001100;
    start = 1; #10;
    start = 0; #100;

    $finish;
  end

endmodule

Day8/uart_tx.vcd
$date
	Sat Apr  4 13:13:13 2026
$end
$version
	Icarus Verilog
$end
$timescale
	1s
$end
$scope module tb_uart_tx $end
$var wire 1 ! tx $end
$var wire 1 " done $end
$var reg 1 # clk $end
$var reg 8 $ data [7:0] $end
$var reg 1 % reset $end
$var reg 1 & start $end
$scope module uut $end
$var wire 1 # clk $end
$var wire 8 ' data [7:0] $end
$var wire 1 % reset $end
$var wire 1 & start $end
$var parameter 2 ( DATA $end
$var parameter 2 ) IDLE $end
$var parameter 2 * START $end
$var parameter 2 + STOP $end
$var reg 3 , bit_count [2:0] $end
$var reg 8 - data_reg [7:0] $end
$var reg 1 " done $end
$var reg 2 . state [1:0] $end
$var reg 1 ! tx $end
$upscope $end
$upscope $end
$enddefinitions $end
$comment Show the parameter values. $end
$dumpall
b11 +
b1 *
b0 )
b10 (
$end
#0
$dumpvars
b0 .
bx -
b0 ,
b0 '
0&
1%
b0 $
0#
0"
1!
$end
#5
1#
#10
0#
1&
b10101010 $
b10101010 '
0%
#15
b10101010 -
b1 .
1#
#20
0#
0&
#25
b10 .
0!
1#
#30
0#
#35
b1 ,
1#
#40
0#
#45
b10 ,
1!
1#
#50
0#
#55
b11 ,
0!
1#
#60
0#
#65
b100 ,
1!
1#
#70
0#
#75
b101 ,
0!
1#
#80
0#
#85
b110 ,
1!
1#
#90
0#
#95
b111 ,
0!
1#
#100
0#
#105
b11 .
1!
1#
#110
0#
#115
b0 .
1"
1#
#120
0#
1&
b11001100 $
b11001100 '
#125
b11001100 -
b1 .
0"
1#
#130
0#
0&
#135
b10 .
b0 ,
0!
1#
#140
0#
#145
b1 ,
1#
#150
0#
#155
b10 ,
1#
#160
0#
#165
b11 ,
1!
1#
#170
0#
#175
b100 ,
1#
#180
0#
#185
b101 ,
0!
1#
#190
0#
#195
b110 ,
1#
#200
0#
#205
b111 ,
1!
1#
#210
0#
#215
b11 .
1#
#220
0#
#225
b0 .
1"
1#
